django_smarttest-0.3.0.dist-info/DESCRIPTION.rst
django_smarttest-0.3.0.dist-info/METADATA
django_smarttest-0.3.0.dist-info/RECORD
django_smarttest-0.3.0.dist-info/WHEEL
django_smarttest-0.3.0.dist-info/metadata.json
django_smarttest-0.3.0.dist-info/top_level.txt
smarttest/__init__.py
smarttest/compat.py
smarttest/decorators.py
smarttest/models.py
smarttest/testcases.py
smarttest/utils.py
smarttest/management/__init__.py
smarttest/management/commands/__init__.py
smarttest/tests/__init__.py
smarttest/tests/test_compat.py
smarttest/tests/test_decorators.py
smarttest/tests/test_testcases.py
smarttest/tests/test_utils.py
